pyetp/__init__.py
pyetp/_version.py
pyetp/client.py
pyetp/config.py
pyetp/resqml_objects.py
pyetp/types.py
pyetp/uri.py
pyetp/utils_arrays.py
pyetp/utils_xml.py
pyetp-0.0.46.dist-info/licenses/LICENSE.md
resqml_objects/__init__.py
resqml_objects/epc_readers.py
resqml_objects/parsers.py
resqml_objects/serializers.py
resqml_objects/surface_helpers.py
resqml_objects/v201/__init__.py
resqml_objects/v201/generated.py
resqml_objects/v201/utils.py
pyetp-0.0.46.dist-info/METADATA
pyetp-0.0.46.dist-info/WHEEL
pyetp-0.0.46.dist-info/top_level.txt
pyetp-0.0.46.dist-info/RECORD
