Metadata-Version: 2.4
Name: pyetp
Version: 0.0.46
Summary: Interface with OSDU RDDMS using ETP protocol
Author-email: Adam Cheng <52572642+adamchengtkc@users.noreply.github.com>
License-Expression: Apache-2.0
Project-URL: homepage, https://github.com/equinor/pyetp
Classifier: Development Status :: 3 - Alpha
Classifier: Programming Language :: Python :: 3.11
Classifier: Programming Language :: Python :: 3.12
Classifier: Programming Language :: Python :: 3.13
Requires-Python: >=3.11
License-File: LICENSE.md
Requires-Dist: numpy>=1.26.0
Requires-Dist: websockets>=15.0
Requires-Dist: lxml>=4.9.4
Requires-Dist: pydantic>=1.10
Requires-Dist: async-timeout>=5.0
Requires-Dist: xtgeo>=4.0.0
Requires-Dist: xsdata>=25.4
Requires-Dist: etpproto>=1.0.7
Dynamic: license-file
